deepstars/__init__.py
deepstars-0.1.0.dist-info/DESCRIPTION.rst
deepstars-0.1.0.dist-info/METADATA
deepstars-0.1.0.dist-info/RECORD
deepstars-0.1.0.dist-info/WHEEL
deepstars-0.1.0.dist-info/entry_points.txt
deepstars-0.1.0.dist-info/metadata.json
deepstars-0.1.0.dist-info/pbr.json
deepstars-0.1.0.dist-info/top_level.txt
