Metadata-Version: 2.0
Name: deepstars
Version: 0.1.0
Summary: Using Deep learning for Automated identification of Supernovae and Hosts
Home-page: https://github.com/daniel-muthukrishna/SNClassifying_Pre-alpha
Author: Daniel Muthukrishna
Author-email: daniel.muthukrishna@gmail.com
License: MIT
Keywords: supernova spectral classification deep learning
Platform: UNKNOWN
Classifier: Development Status :: 3 - Alpha
Classifier: Intended Audience :: Science/Research
Classifier: Topic :: Scientific/Engineering :: Astronomy
Classifier: License :: OSI Approved :: MIT License
Classifier: Programming Language :: Python :: 2
Classifier: Programming Language :: Python :: 3
Requires-Dist: numpy
Requires-Dist: scipy
Requires-Dist: specutils
